{
    "data": {
        "18F/domain-scan": {
            "labContributors": {
                "nodes": [
                    "IanLee1521"
                ]
            },
            "nameWithOwner": "18F/domain-scan"
        },
        "AIDungeon/AIDungeon": {
            "labContributors": {
                "nodes": [
                    "ben-bay"
                ]
            },
            "nameWithOwner": "AIDungeon/AIDungeon"
        },
        "AMReX-Astro/Nyx": {
            "labContributors": {
                "nodes": [
                    "cyrush"
                ]
            },
            "nameWithOwner": "AMReX-Astro/Nyx"
        },
        "AMReX-Codes/ATPESC-codes": {
            "labContributors": {
                "nodes": [
                    "gardner48"
                ]
            },
            "nameWithOwner": "AMReX-Codes/ATPESC-codes"
        },
        "AMReX-Codes/amrex": {
            "labContributors": {
                "nodes": [
                    "balos1",
                    "cyrush"
                ]
            },
            "nameWithOwner": "AMReX-Codes/amrex"
        },
        "ATOMconsortium/AMPL": {
            "labContributors": {
                "nodes": [
                    "amandajean119"
                ]
            },
            "nameWithOwner": "ATOMconsortium/AMPL"
        },
        "Alpine-DAV/algorithms": {
            "labContributors": {
                "nodes": [
                    "cyrush"
                ]
            },
            "nameWithOwner": "Alpine-DAV/algorithms"
        },
        "Alpine-DAV/ap_compositor": {
            "labContributors": {
                "nodes": [
                    "mclarsen"
                ]
            },
            "nameWithOwner": "Alpine-DAV/ap_compositor"
        },
        "Alpine-DAV/ascent_gpu_dashboard": {
            "labContributors": {
                "nodes": [
                    "mclarsen"
                ]
            },
            "nameWithOwner": "Alpine-DAV/ascent_gpu_dashboard"
        },
        "Alpine-DAV/hmc2019": {
            "labContributors": {
                "nodes": [
                    "cyrush"
                ]
            },
            "nameWithOwner": "Alpine-DAV/hmc2019"
        },
        "Alpine-DAV/sw4_uberenv": {
            "labContributors": {
                "nodes": [
                    "mclarsen"
                ]
            },
            "nameWithOwner": "Alpine-DAV/sw4_uberenv"
        },
        "Alpine-DAV/vtk-h": {
            "labContributors": {
                "nodes": [
                    "cyrush",
                    "lee-busby",
                    "mclarsen"
                ]
            },
            "nameWithOwner": "Alpine-DAV/vtk-h"
        },
        "AndrewRadev/splitjoin.vim": {
            "labContributors": {
                "nodes": [
                    "sbromberger"
                ]
            },
            "nameWithOwner": "AndrewRadev/splitjoin.vim"
        },
        "Argonne-National-Laboratory/PIPS": {
            "labContributors": {
                "nodes": [
                    "cnpetra"
                ]
            },
            "nameWithOwner": "Argonne-National-Laboratory/PIPS"
        },
        "BlackrockDigital/startbootstrap-sb-admin-2": {
            "labContributors": {
                "nodes": [
                    "cheizer"
                ]
            },
            "nameWithOwner": "BlackrockDigital/startbootstrap-sb-admin-2"
        },
        "CCSI-Toolset/FOQUS": {
            "labContributors": {
                "nodes": [
                    "ngbrenda",
                    "sotorrio1"
                ]
            },
            "nameWithOwner": "CCSI-Toolset/FOQUS"
        },
        "CEED/Remhos": {
            "labContributors": {
                "nodes": [
                    "artv3",
                    "tzanio",
                    "v-dobrev"
                ]
            },
            "nameWithOwner": "CEED/Remhos"
        },
        "CLIUtils/CLI11": {
            "labContributors": {
                "nodes": [
                    "nightlark",
                    "phlptp"
                ]
            },
            "nameWithOwner": "CLIUtils/CLI11"
        },
        "CSUChico-CINS465/Assignment-2-Django-Hello-World": {
            "labContributors": {
                "nodes": [
                    "javawolfpack"
                ]
            },
            "nameWithOwner": "CSUChico-CINS465/Assignment-2-Django-Hello-World"
        },
        "CSUChico-CINS465/CINS465-Course-Materials": {
            "labContributors": {
                "nodes": [
                    "javawolfpack"
                ]
            },
            "nameWithOwner": "CSUChico-CINS465/CINS465-Course-Materials"
        },
        "CSUChico-CINS465/CINS465-F19-Examples": {
            "labContributors": {
                "nodes": [
                    "javawolfpack"
                ]
            },
            "nameWithOwner": "CSUChico-CINS465/CINS465-F19-Examples"
        },
        "CSUChico-CINS465/CINS465-Project": {
            "labContributors": {
                "nodes": [
                    "javawolfpack"
                ]
            },
            "nameWithOwner": "CSUChico-CINS465/CINS465-Project"
        },
        "CSUChico-CINS465/CINS465-S19-Examples": {
            "labContributors": {
                "nodes": [
                    "javawolfpack"
                ]
            },
            "nameWithOwner": "CSUChico-CINS465/CINS465-S19-Examples"
        },
        "CSUChico-CINS465/CINS465-S20-Examples": {
            "labContributors": {
                "nodes": [
                    "javawolfpack"
                ]
            },
            "nameWithOwner": "CSUChico-CINS465/CINS465-S20-Examples"
        },
        "CSUChico-CSCI221/DataLabWriteUp": {
            "labContributors": {
                "nodes": [
                    "javawolfpack"
                ]
            },
            "nameWithOwner": "CSUChico-CSCI221/DataLabWriteUp"
        },
        "CSUChico-CSCI340/CSCI340-Course-Materials": {
            "labContributors": {
                "nodes": [
                    "javawolfpack"
                ]
            },
            "nameWithOwner": "CSUChico-CSCI340/CSCI340-Course-Materials"
        },
        "CSUChico-CSCI340/CSCI340-DNS-Name-Resolution-Engine": {
            "labContributors": {
                "nodes": [
                    "javawolfpack"
                ]
            },
            "nameWithOwner": "CSUChico-CSCI340/CSCI340-DNS-Name-Resolution-Engine"
        },
        "CSUChico-CSCI340/CSCI340-KernelHacking": {
            "labContributors": {
                "nodes": [
                    "javawolfpack"
                ]
            },
            "nameWithOwner": "CSUChico-CSCI340/CSCI340-KernelHacking"
        },
        "CSUChico-CSCI340/CSCI340-Scheduler": {
            "labContributors": {
                "nodes": [
                    "javawolfpack"
                ]
            },
            "nameWithOwner": "CSUChico-CSCI340/CSCI340-Scheduler"
        },
        "CSUChico-CSCI340/CSCI340-Shell-Assignment": {
            "labContributors": {
                "nodes": [
                    "javawolfpack"
                ]
            },
            "nameWithOwner": "CSUChico-CSCI340/CSCI340-Shell-Assignment"
        },
        "CSUChico-CSCI567/CSCI567-Course-Materials": {
            "labContributors": {
                "nodes": [
                    "javawolfpack"
                ]
            },
            "nameWithOwner": "CSUChico-CSCI567/CSCI567-Course-Materials"
        },
        "CSUChico-CSCI567/CSCI567_S20_Examples": {
            "labContributors": {
                "nodes": [
                    "javawolfpack"
                ]
            },
            "nameWithOwner": "CSUChico-CSCI567/CSCI567_S20_Examples"
        },
        "CSUChico/ACM-W-Python-Demo-Spring-2020": {
            "labContributors": {
                "nodes": [
                    "javawolfpack"
                ]
            },
            "nameWithOwner": "CSUChico/ACM-W-Python-Demo-Spring-2020"
        },
        "CachetHQ/Cachet": {
            "labContributors": {
                "nodes": [
                    "joe-eklund"
                ]
            },
            "nameWithOwner": "CachetHQ/Cachet"
        },
        "Collegeville/CW3S19": {
            "labContributors": {
                "nodes": [
                    "markcmiller86",
                    "osborn9"
                ]
            },
            "nameWithOwner": "Collegeville/CW3S19"
        },
        "CrabBucket/AngularGameProject": {
            "labContributors": {
                "nodes": [
                    "angfl97"
                ]
            },
            "nameWithOwner": "CrabBucket/AngularGameProject"
        },
        "E3SM-Project/e3sm_diags": {
            "labContributors": {
                "nodes": [
                    "forsyth2"
                ]
            },
            "nameWithOwner": "E3SM-Project/e3sm_diags"
        },
        "E3SM-Project/zstash": {
            "labContributors": {
                "nodes": [
                    "forsyth2"
                ]
            },
            "nameWithOwner": "E3SM-Project/zstash"
        },
        "E4S-Project/ECP-ST-CAR-PUBLIC": {
            "labContributors": {
                "nodes": [
                    "cswoodward",
                    "tgamblin",
                    "ulrikeyang"
                ]
            },
            "nameWithOwner": "E4S-Project/ECP-ST-CAR-PUBLIC"
        },
        "E4S-Project/e4s-stacks": {
            "labContributors": {
                "nodes": [
                    "tgamblin"
                ]
            },
            "nameWithOwner": "E4S-Project/e4s-stacks"
        },
        "ECP-CANDLE/Benchmarks": {
            "labContributors": {
                "nodes": [
                    "adammoody"
                ]
            },
            "nameWithOwner": "ECP-CANDLE/Benchmarks"
        },
        "ECP-CANDLE/Supervisor": {
            "labContributors": {
                "nodes": [
                    "adammoody"
                ]
            },
            "nameWithOwner": "ECP-CANDLE/Supervisor"
        },
        "ECP-WarpX/WarpX": {
            "labContributors": {
                "nodes": [
                    "cyrush"
                ]
            },
            "nameWithOwner": "ECP-WarpX/WarpX"
        },
        "FATSLiM/fatslim": {
            "labContributors": {
                "nodes": [
                    "bhatiaharsh"
                ]
            },
            "nameWithOwner": "FATSLiM/fatslim"
        },
        "FPBench/FPBench.github.io": {
            "labContributors": {
                "nodes": [
                    "lam2mo"
                ]
            },
            "nameWithOwner": "FPBench/FPBench.github.io"
        },
        "FalconOVII/CINS465_WebSite": {
            "labContributors": {
                "nodes": [
                    "javawolfpack"
                ]
            },
            "nameWithOwner": "FalconOVII/CINS465_WebSite"
        },
        "FriendsofECCE/ECCE": {
            "labContributors": {
                "nodes": [
                    "joshuata"
                ]
            },
            "nameWithOwner": "FriendsofECCE/ECCE"
        },
        "GEOSX/cxx-utilities": {
            "labContributors": {
                "nodes": [
                    "bmhan12",
                    "corbett5",
                    "rrsettgast"
                ]
            },
            "nameWithOwner": "GEOSX/cxx-utilities"
        },
        "GSA/code-gov-data": {
            "labContributors": {
                "nodes": [
                    "IanLee1521"
                ]
            },
            "nameWithOwner": "GSA/code-gov-data"
        },
        "Gabrielcarvfer/NS3": {
            "labContributors": {
                "nodes": [
                    "nightlark"
                ]
            },
            "nameWithOwner": "Gabrielcarvfer/NS3"
        },
        "Galvant/InstrumentKit": {
            "labContributors": {
                "nodes": [
                    "trappitsch"
                ]
            },
            "nameWithOwner": "Galvant/InstrumentKit"
        },
        "Gaurav-Shankar/check-username": {
            "labContributors": {
                "nodes": [
                    "gonsie"
                ]
            },
            "nameWithOwner": "Gaurav-Shankar/check-username"
        },
        "GridTools/gt4py": {
            "labContributors": {
                "nodes": [
                    "jdahm"
                ]
            },
            "nameWithOwner": "GridTools/gt4py"
        },
        "HPCPowerStack/hpcpowerstack.github.io": {
            "labContributors": {
                "nodes": [
                    "amarathe84",
                    "schulzm",
                    "slabasan"
                ]
            },
            "nameWithOwner": "HPCPowerStack/hpcpowerstack.github.io"
        },
        "Heatherms27/BlogPost": {
            "labContributors": {
                "nodes": [
                    "gonsie"
                ]
            },
            "nameWithOwner": "Heatherms27/BlogPost"
        },
        "Homebrew/homebrew-cask": {
            "labContributors": {
                "nodes": [
                    "joshuata"
                ]
            },
            "nameWithOwner": "Homebrew/homebrew-cask"
        },
        "Homebrew/homebrew-core": {
            "labContributors": {
                "nodes": [
                    "sbromberger"
                ]
            },
            "nameWithOwner": "Homebrew/homebrew-core"
        },
        "IBM/CAST": {
            "labContributors": {
                "nodes": [
                    "adammoody",
                    "morrone"
                ]
            },
            "nameWithOwner": "IBM/CAST"
        },
        "IHPCSS/ihpcss.github.io": {
            "labContributors": {
                "nodes": [
                    "gonsie"
                ]
            },
            "nameWithOwner": "IHPCSS/ihpcss.github.io"
        },
        "JMU-CS/less-java": {
            "labContributors": {
                "nodes": [
                    "lam2mo"
                ]
            },
            "nameWithOwner": "JMU-CS/less-java"
        },
        "JuliaArrays/FillArrays.jl": {
            "labContributors": {
                "nodes": [
                    "sbromberger"
                ]
            },
            "nameWithOwner": "JuliaArrays/FillArrays.jl"
        },
        "JuliaCI/BenchmarkTools.jl": {
            "labContributors": {
                "nodes": [
                    "sbromberger"
                ]
            },
            "nameWithOwner": "JuliaCI/BenchmarkTools.jl"
        },
        "JuliaCI/Coverage.jl": {
            "labContributors": {
                "nodes": [
                    "sbromberger"
                ]
            },
            "nameWithOwner": "JuliaCI/Coverage.jl"
        },
        "JuliaCollections/DataStructures.jl": {
            "labContributors": {
                "nodes": [
                    "sbromberger"
                ]
            },
            "nameWithOwner": "JuliaCollections/DataStructures.jl"
        },
        "JuliaGraphs/GraphIO.jl": {
            "labContributors": {
                "nodes": [
                    "sbromberger"
                ]
            },
            "nameWithOwner": "JuliaGraphs/GraphIO.jl"
        },
        "JuliaGraphs/GraphPlot.jl": {
            "labContributors": {
                "nodes": [
                    "sbromberger"
                ]
            },
            "nameWithOwner": "JuliaGraphs/GraphPlot.jl"
        },
        "JuliaGraphs/JuliaGraphs-meta": {
            "labContributors": {
                "nodes": [
                    "sbromberger"
                ]
            },
            "nameWithOwner": "JuliaGraphs/JuliaGraphs-meta"
        },
        "JuliaGraphs/LightGraphs.jl": {
            "labContributors": {
                "nodes": [
                    "sbromberger"
                ]
            },
            "nameWithOwner": "JuliaGraphs/LightGraphs.jl"
        },
        "JuliaGraphs/MetaGraphs.jl": {
            "labContributors": {
                "nodes": [
                    "sbromberger"
                ]
            },
            "nameWithOwner": "JuliaGraphs/MetaGraphs.jl"
        },
        "JuliaGraphs/SNAPDatasets.jl": {
            "labContributors": {
                "nodes": [
                    "sbromberger"
                ]
            },
            "nameWithOwner": "JuliaGraphs/SNAPDatasets.jl"
        },
        "JuliaGraphs/SimpleWeightedGraphs.jl": {
            "labContributors": {
                "nodes": [
                    "sbromberger"
                ]
            },
            "nameWithOwner": "JuliaGraphs/SimpleWeightedGraphs.jl"
        },
        "JuliaGraphs/StaticGraphs.jl": {
            "labContributors": {
                "nodes": [
                    "sbromberger"
                ]
            },
            "nameWithOwner": "JuliaGraphs/StaticGraphs.jl"
        },
        "JuliaGraphs/juliagraphs.github.io": {
            "labContributors": {
                "nodes": [
                    "sbromberger"
                ]
            },
            "nameWithOwner": "JuliaGraphs/juliagraphs.github.io"
        },
        "JuliaIO/JLD2.jl": {
            "labContributors": {
                "nodes": [
                    "sbromberger"
                ]
            },
            "nameWithOwner": "JuliaIO/JLD2.jl"
        },
        "JuliaLang/Pkg.jl": {
            "labContributors": {
                "nodes": [
                    "sbromberger"
                ]
            },
            "nameWithOwner": "JuliaLang/Pkg.jl"
        },
        "JuliaLang/julia": {
            "labContributors": {
                "nodes": [
                    "sbromberger"
                ]
            },
            "nameWithOwner": "JuliaLang/julia"
        },
        "JuliaLang/www.julialang.org": {
            "labContributors": {
                "nodes": [
                    "sbromberger"
                ]
            },
            "nameWithOwner": "JuliaLang/www.julialang.org"
        },
        "JuliaPackaging/Yggdrasil": {
            "labContributors": {
                "nodes": [
                    "nightlark"
                ]
            },
            "nameWithOwner": "JuliaPackaging/Yggdrasil"
        },
        "Ketouem/flask-boto3": {
            "labContributors": {
                "nodes": [
                    "cheizer"
                ]
            },
            "nameWithOwner": "Ketouem/flask-boto3"
        },
        "MDSplus/mdsplus": {
            "labContributors": {
                "nodes": [
                    "brugger1"
                ]
            },
            "nameWithOwner": "MDSplus/mdsplus"
        },
        "Mantevo/mantevo.github.io": {
            "labContributors": {
                "nodes": [
                    "amarathe84",
                    "keitat"
                ]
            },
            "nameWithOwner": "Mantevo/mantevo.github.io"
        },
        "Mantevo/miniMD": {
            "labContributors": {
                "nodes": [
                    "keitat"
                ]
            },
            "nameWithOwner": "Mantevo/miniMD"
        },
        "ManuelMeraz/Tracker": {
            "labContributors": {
                "nodes": [
                    "madonnay"
                ]
            },
            "nameWithOwner": "ManuelMeraz/Tracker"
        },
        "MarkBaggett/werejugo": {
            "labContributors": {
                "nodes": [
                    "IanLee1521"
                ]
            },
            "nameWithOwner": "MarkBaggett/werejugo"
        },
        "Mergifyio/mergify-engine": {
            "labContributors": {
                "nodes": [
                    "SteVwonder"
                ]
            },
            "nameWithOwner": "Mergifyio/mergify-engine"
        },
        "MeteoSwiss-APN/dawn": {
            "labContributors": {
                "nodes": [
                    "jdahm"
                ]
            },
            "nameWithOwner": "MeteoSwiss-APN/dawn"
        },
        "MeteoSwiss-APN/yoda": {
            "labContributors": {
                "nodes": [
                    "jdahm"
                ]
            },
            "nameWithOwner": "MeteoSwiss-APN/yoda"
        },
        "NCAR/VAPOR-SupportPage": {
            "labContributors": {
                "nodes": [
                    "kalundquist"
                ]
            },
            "nameWithOwner": "NCAR/VAPOR-SupportPage"
        },
        "NERSC/instrumentation-benchmark": {
            "labContributors": {
                "nodes": [
                    "daboehme"
                ]
            },
            "nameWithOwner": "NERSC/instrumentation-benchmark"
        },
        "NVIDIA/AMGX": {
            "labContributors": {
                "nodes": [
                    "artv3"
                ]
            },
            "nameWithOwner": "NVIDIA/AMGX"
        },
        "NVIDIA/nccl": {
            "labContributors": {
                "nodes": [
                    "naoyam"
                ]
            },
            "nameWithOwner": "NVIDIA/nccl"
        },
        "Nek5000/Nek5000": {
            "labContributors": {
                "nodes": [
                    "kmittal2"
                ]
            },
            "nameWithOwner": "Nek5000/Nek5000"
        },
        "Nek5000/gslib": {
            "labContributors": {
                "nodes": [
                    "kmittal2"
                ]
            },
            "nameWithOwner": "Nek5000/gslib"
        },
        "Phlow/feeling-responsive": {
            "labContributors": {
                "nodes": [
                    "brugger1"
                ]
            },
            "nameWithOwner": "Phlow/feeling-responsive"
        },
        "PyTorchLightning/pytorch-lightning": {
            "labContributors": {
                "nodes": [
                    "rblake-llnl"
                ]
            },
            "nameWithOwner": "PyTorchLightning/pytorch-lightning"
        },
        "QMCPACK/qmcpack": {
            "labContributors": {
                "nodes": [
                    "correaa"
                ]
            },
            "nameWithOwner": "QMCPACK/qmcpack"
        },
        "ROCm-Developer-Tools/aomp": {
            "labContributors": {
                "nodes": [
                    "trws"
                ]
            },
            "nameWithOwner": "ROCm-Developer-Tools/aomp"
        },
        "ROCm-Developer-Tools/rocprofiler": {
            "labContributors": {
                "nodes": [
                    "camierjs"
                ]
            },
            "nameWithOwner": "ROCm-Developer-Tools/rocprofiler"
        },
        "ROCmSoftwarePlatform/rocPRIM": {
            "labContributors": {
                "nodes": [
                    "MrBurmark"
                ]
            },
            "nameWithOwner": "ROCmSoftwarePlatform/rocPRIM"
        },
        "ROSS-org/ROSS": {
            "labContributors": {
                "nodes": [
                    "gonsie"
                ]
            },
            "nameWithOwner": "ROSS-org/ROSS"
        },
        "ROSS-org/ross-org.github.io": {
            "labContributors": {
                "nodes": [
                    "gonsie"
                ]
            },
            "nameWithOwner": "ROSS-org/ross-org.github.io"
        },
        "ROSS-org/template-model": {
            "labContributors": {
                "nodes": [
                    "gonsie"
                ]
            },
            "nameWithOwner": "ROSS-org/template-model"
        },
        "Reference-LAPACK/lapack": {
            "labContributors": {
                "nodes": [
                    "corbett5"
                ]
            },
            "nameWithOwner": "Reference-LAPACK/lapack"
        },
        "SC-Tech-Program/FAQs": {
            "labContributors": {
                "nodes": [
                    "kathrynmohror"
                ]
            },
            "nameWithOwner": "SC-Tech-Program/FAQs"
        },
        "SNiPER-Framework/sniper": {
            "labContributors": {
                "nodes": [
                    "samusangio"
                ]
            },
            "nameWithOwner": "SNiPER-Framework/sniper"
        },
        "STEllAR-GROUP/hpx": {
            "labContributors": {
                "nodes": [
                    "keitat"
                ]
            },
            "nameWithOwner": "STEllAR-GROUP/hpx"
        },
        "Sandia-OpenSHMEM/SOS": {
            "labContributors": {
                "nodes": [
                    "benson31"
                ]
            },
            "nameWithOwner": "Sandia-OpenSHMEM/SOS"
        },
        "Sarcasm/irony-mode": {
            "labContributors": {
                "nodes": [
                    "goxberry"
                ]
            },
            "nameWithOwner": "Sarcasm/irony-mode"
        },
        "Semmle/ql": {
            "labContributors": {
                "nodes": [
                    "SteVwonder"
                ]
            },
            "nameWithOwner": "Semmle/ql"
        },
        "Starbix/docker-synclounge": {
            "labContributors": {
                "nodes": [
                    "joshuata"
                ]
            },
            "nameWithOwner": "Starbix/docker-synclounge"
        },
        "TeachRaccooon/Department-Honors-Thesis": {
            "labContributors": {
                "nodes": [
                    "willkill07"
                ]
            },
            "nameWithOwner": "TeachRaccooon/Department-Honors-Thesis"
        },
        "UA-SRC-data/geo-visualization": {
            "labContributors": {
                "nodes": [
                    "kisaacs"
                ]
            },
            "nameWithOwner": "UA-SRC-data/geo-visualization"
        },
        "UACSC343Spring2019/ha1a-base": {
            "labContributors": {
                "nodes": [
                    "kisaacs"
                ]
            },
            "nameWithOwner": "UACSC343Spring2019/ha1a-base"
        },
        "UCL/GreatCMakeCookOff": {
            "labContributors": {
                "nodes": [
                    "goxberry"
                ]
            },
            "nameWithOwner": "UCL/GreatCMakeCookOff"
        },
        "UIUC-PPL/charm": {
            "labContributors": {
                "nodes": [
                    "harshithamenon",
                    "nikhil-jain"
                ]
            },
            "nameWithOwner": "UIUC-PPL/charm"
        },
        "USCiLab/cereal": {
            "labContributors": {
                "nodes": [
                    "JaeseungYeom"
                ]
            },
            "nameWithOwner": "USCiLab/cereal"
        },
        "UoB-HPC/hal3d": {
            "labContributors": {
                "nodes": [
                    "jdahm"
                ]
            },
            "nameWithOwner": "UoB-HPC/hal3d"
        },
        "ValveSoftware/steam-for-linux": {
            "labContributors": {
                "nodes": [
                    "kdickerson"
                ]
            },
            "nameWithOwner": "ValveSoftware/steam-for-linux"
        },
        "VulcanClimateModeling/fv3gfs-fortran": {
            "labContributors": {
                "nodes": [
                    "jdahm"
                ]
            },
            "nameWithOwner": "VulcanClimateModeling/fv3gfs-fortran"
        },
        "VulcanClimateModeling/gt4py": {
            "labContributors": {
                "nodes": [
                    "jdahm"
                ]
            },
            "nameWithOwner": "VulcanClimateModeling/gt4py"
        },
        "WomeninHPC/mentoring": {
            "labContributors": {
                "nodes": [
                    "gonsie"
                ]
            },
            "nameWithOwner": "WomeninHPC/mentoring"
        },
        "WorldHealthOrganization/app": {
            "labContributors": {
                "nodes": [
                    "nightlark"
                ]
            },
            "nameWithOwner": "WorldHealthOrganization/app"
        },
        "ZipArchive/ZipArchive": {
            "labContributors": {
                "nodes": [
                    "cheizer"
                ]
            },
            "nameWithOwner": "ZipArchive/ZipArchive"
        },
        "accelerated-odes/acclerated-odes-examples": {
            "labContributors": {
                "nodes": [
                    "balos1"
                ]
            },
            "nameWithOwner": "accelerated-odes/acclerated-odes-examples"
        },
        "achmelev/lilac": {
            "labContributors": {
                "nodes": [
                    "Thrameos"
                ]
            },
            "nameWithOwner": "achmelev/lilac"
        },
        "acquia/blt": {
            "labContributors": {
                "nodes": [
                    "shelane"
                ]
            },
            "nameWithOwner": "acquia/blt"
        },
        "acquia/cloud-hooks": {
            "labContributors": {
                "nodes": [
                    "shelane"
                ]
            },
            "nameWithOwner": "acquia/cloud-hooks"
        },
        "actions/virtual-environments": {
            "labContributors": {
                "nodes": [
                    "nightlark"
                ]
            },
            "nameWithOwner": "actions/virtual-environments"
        },
        "adhdproject/adhdproject.github.io": {
            "labContributors": {
                "nodes": [
                    "IanLee1521"
                ]
            },
            "nameWithOwner": "adhdproject/adhdproject.github.io"
        },
        "afd998/QA-engine": {
            "labContributors": {
                "nodes": [
                    "JamesTaliaferro"
                ]
            },
            "nameWithOwner": "afd998/QA-engine"
        },
        "agronholm/apscheduler": {
            "labContributors": {
                "nodes": [
                    "cheizer"
                ]
            },
            "nameWithOwner": "agronholm/apscheduler"
        },
        "aldorona/contur": {
            "labContributors": {
                "nodes": [
                    "rchen20"
                ]
            },
            "nameWithOwner": "aldorona/contur"
        },
        "alex-r-bigelow/sanitized-wrangling-codes": {
            "labContributors": {
                "nodes": [
                    "kisaacs"
                ]
            },
            "nameWithOwner": "alex-r-bigelow/sanitized-wrangling-codes"
        },
        "anikau31/systemc-clang": {
            "labContributors": {
                "nodes": [
                    "mayagokhale"
                ]
            },
            "nameWithOwner": "anikau31/systemc-clang"
        },
        "archspec/archspec": {
            "labContributors": {
                "nodes": [
                    "tgamblin"
                ]
            },
            "nameWithOwner": "archspec/archspec"
        },
        "asherliu/researchHOWTO": {
            "labContributors": {
                "nodes": [
                    "chunhualiao"
                ]
            },
            "nameWithOwner": "asherliu/researchHOWTO"
        },
        "autoconf-archive/autoconf-archive": {
            "labContributors": {
                "nodes": [
                    "goxberry"
                ]
            },
            "nameWithOwner": "autoconf-archive/autoconf-archive"
        },
        "baztian/jaydebeapi": {
            "labContributors": {
                "nodes": [
                    "Thrameos"
                ]
            },
            "nameWithOwner": "baztian/jaydebeapi"
        },
        "betterscientificsoftware/PSIP-Tools": {
            "labContributors": {
                "nodes": [
                    "gonsie"
                ]
            },
            "nameWithOwner": "betterscientificsoftware/PSIP-Tools"
        },
        "betterscientificsoftware/betterscientificsoftware.github.io": {
            "labContributors": {
                "nodes": [
                    "gonsie",
                    "markcmiller86"
                ]
            },
            "nameWithOwner": "betterscientificsoftware/betterscientificsoftware.github.io"
        },
        "betterscientificsoftware/hello-heat-equation": {
            "labContributors": {
                "nodes": [
                    "gonsie",
                    "markcmiller86"
                ]
            },
            "nameWithOwner": "betterscientificsoftware/hello-heat-equation"
        },
        "betterscientificsoftware/images": {
            "labContributors": {
                "nodes": [
                    "gonsie",
                    "markcmiller86"
                ]
            },
            "nameWithOwner": "betterscientificsoftware/images"
        },
        "bhatiaharsh/spack": {
            "labContributors": {
                "nodes": [
                    "FrankD412"
                ]
            },
            "nameWithOwner": "bhatiaharsh/spack"
        },
        "blinksh/blink": {
            "labContributors": {
                "nodes": [
                    "sbromberger"
                ]
            },
            "nameWithOwner": "blinksh/blink"
        },
        "boostorg/fusion": {
            "labContributors": {
                "nodes": [
                    "correaa"
                ]
            },
            "nameWithOwner": "boostorg/fusion"
        },
        "boostorg/serialization": {
            "labContributors": {
                "nodes": [
                    "correaa"
                ]
            },
            "nameWithOwner": "boostorg/serialization"
        },
        "bssw-psip/bssw-psip.github.io": {
            "labContributors": {
                "nodes": [
                    "gonsie"
                ]
            },
            "nameWithOwner": "bssw-psip/bssw-psip.github.io"
        },
        "bssw-psip/practice-guides": {
            "labContributors": {
                "nodes": [
                    "gonsie",
                    "markcmiller86"
                ]
            },
            "nameWithOwner": "bssw-psip/practice-guides"
        },
        "bssw-psip/ptc-catalog": {
            "labContributors": {
                "nodes": [
                    "gonsie",
                    "markcmiller86"
                ]
            },
            "nameWithOwner": "bssw-psip/ptc-catalog"
        },
        "build-environment/hbb-script": {
            "labContributors": {
                "nodes": [
                    "nightlark"
                ]
            },
            "nameWithOwner": "build-environment/hbb-script"
        },
        "bvanessen/lbann": {
            "labContributors": {
                "nodes": [
                    "benson31",
                    "timmoon10"
                ]
            },
            "nameWithOwner": "bvanessen/lbann"
        },
        "carpentries/equity-and-inclusion": {
            "labContributors": {
                "nodes": [
                    "markcmiller86"
                ]
            },
            "nameWithOwner": "carpentries/equity-and-inclusion"
        },
        "cdwdirect/cleverleaf": {
            "labContributors": {
                "nodes": [
                    "ggeorgakoudis"
                ]
            },
            "nameWithOwner": "cdwdirect/cleverleaf"
        },
        "chethega/BitmapGraphs": {
            "labContributors": {
                "nodes": [
                    "sbromberger"
                ]
            },
            "nameWithOwner": "chethega/BitmapGraphs"
        },
        "chipsec/chipsec": {
            "labContributors": {
                "nodes": [
                    "rountree"
                ]
            },
            "nameWithOwner": "chipsec/chipsec"
        },
        "christianselig/apollo-bugs": {
            "labContributors": {
                "nodes": [
                    "joshuata"
                ]
            },
            "nameWithOwner": "christianselig/apollo-bugs"
        },
        "cisagov/pshtt": {
            "labContributors": {
                "nodes": [
                    "IanLee1521"
                ]
            },
            "nameWithOwner": "cisagov/pshtt"
        },
        "cmaul85/webProject": {
            "labContributors": {
                "nodes": [
                    "javawolfpack"
                ]
            },
            "nameWithOwner": "cmaul85/webProject"
        },
        "codes-org/codes": {
            "labContributors": {
                "nodes": [
                    "nightlark"
                ]
            },
            "nameWithOwner": "codes-org/codes"
        },
        "coin-or/Ipopt": {
            "labContributors": {
                "nodes": [
                    "cnpetra"
                ]
            },
            "nameWithOwner": "coin-or/Ipopt"
        },
        "conda-forge/conduit-feedstock": {
            "labContributors": {
                "nodes": [
                    "cyrush"
                ]
            },
            "nameWithOwner": "conda-forge/conduit-feedstock"
        },
        "conda-forge/helics-feedstock": {
            "labContributors": {
                "nodes": [
                    "nightlark"
                ]
            },
            "nameWithOwner": "conda-forge/helics-feedstock"
        },
        "conda-forge/staged-recipes": {
            "labContributors": {
                "nodes": [
                    "cyrush"
                ]
            },
            "nameWithOwner": "conda-forge/staged-recipes"
        },
        "conda/conda": {
            "labContributors": {
                "nodes": [
                    "dstrozzi"
                ]
            },
            "nameWithOwner": "conda/conda"
        },
        "cornellius-gp/gpytorch": {
            "labContributors": {
                "nodes": [
                    "tadesautels"
                ]
            },
            "nameWithOwner": "cornellius-gp/gpytorch"
        },
        "correctness-workshop/2019": {
            "labContributors": {
                "nodes": [
                    "ilagunap"
                ]
            },
            "nameWithOwner": "correctness-workshop/2019"
        },
        "crafthpc/craft": {
            "labContributors": {
                "nodes": [
                    "lam2mo"
                ]
            },
            "nameWithOwner": "crafthpc/craft"
        },
        "crafthpc/floatsmith": {
            "labContributors": {
                "nodes": [
                    "lam2mo"
                ]
            },
            "nameWithOwner": "crafthpc/floatsmith"
        },
        "crafthpc/sc18poster": {
            "labContributors": {
                "nodes": [
                    "lam2mo"
                ]
            },
            "nameWithOwner": "crafthpc/sc18poster"
        },
        "crafthpc/shval": {
            "labContributors": {
                "nodes": [
                    "lam2mo"
                ]
            },
            "nameWithOwner": "crafthpc/shval"
        },
        "csuchico-csci551/AutomaticVectorization": {
            "labContributors": {
                "nodes": [
                    "javawolfpack"
                ]
            },
            "nameWithOwner": "csuchico-csci551/AutomaticVectorization"
        },
        "csuchico-csci551/CSCI551-Course-Materials": {
            "labContributors": {
                "nodes": [
                    "javawolfpack"
                ]
            },
            "nameWithOwner": "csuchico-csci551/CSCI551-Course-Materials"
        },
        "csuchico-csci551/CodeExamplesF19": {
            "labContributors": {
                "nodes": [
                    "javawolfpack"
                ]
            },
            "nameWithOwner": "csuchico-csci551/CodeExamplesF19"
        },
        "csuchico-csci551/Conway-s-Game-of-Life-MPI": {
            "labContributors": {
                "nodes": [
                    "javawolfpack"
                ]
            },
            "nameWithOwner": "csuchico-csci551/Conway-s-Game-of-Life-MPI"
        },
        "csuchico-csci551/JetsonCluster": {
            "labContributors": {
                "nodes": [
                    "javawolfpack"
                ]
            },
            "nameWithOwner": "csuchico-csci551/JetsonCluster"
        },
        "csuchico-csci551/Performance-Lab": {
            "labContributors": {
                "nodes": [
                    "javawolfpack"
                ]
            },
            "nameWithOwner": "csuchico-csci551/Performance-Lab"
        },
        "csuchico-csci551/Spark": {
            "labContributors": {
                "nodes": [
                    "javawolfpack"
                ]
            },
            "nameWithOwner": "csuchico-csci551/Spark"
        },
        "csuchico-csci551/compute-instances": {
            "labContributors": {
                "nodes": [
                    "javawolfpack"
                ]
            },
            "nameWithOwner": "csuchico-csci551/compute-instances"
        },
        "csuchico-csci551/slurm-gcp": {
            "labContributors": {
                "nodes": [
                    "javawolfpack"
                ]
            },
            "nameWithOwner": "csuchico-csci551/slurm-gcp"
        },
        "cyclus/cyclus": {
            "labContributors": {
                "nodes": [
                    "yarden-livnat"
                ]
            },
            "nameWithOwner": "cyclus/cyclus"
        },
        "daboehme/Caliper": {
            "labContributors": {
                "nodes": [
                    "mplegendre"
                ]
            },
            "nameWithOwner": "daboehme/Caliper"
        },
        "dacracot-algorithmists/tox": {
            "labContributors": {
                "nodes": [
                    "dacracot"
                ]
            },
            "nameWithOwner": "dacracot-algorithmists/tox"
        },
        "dask/dask": {
            "labContributors": {
                "nodes": [
                    "mclarsen"
                ]
            },
            "nameWithOwner": "dask/dask"
        },
        "davidhalter/jedi": {
            "labContributors": {
                "nodes": [
                    "Thrameos"
                ]
            },
            "nameWithOwner": "davidhalter/jedi"
        },
        "delphix/zfs": {
            "labContributors": {
                "nodes": [
                    "behlendorf"
                ]
            },
            "nameWithOwner": "delphix/zfs"
        },
        "dense-analysis/ale": {
            "labContributors": {
                "nodes": [
                    "sbromberger"
                ]
            },
            "nameWithOwner": "dense-analysis/ale"
        },
        "desul/desul": {
            "labContributors": {
                "nodes": [
                    "davidbeckingsale",
                    "trws"
                ]
            },
            "nameWithOwner": "desul/desul"
        },
        "django-compressor/django-compressor": {
            "labContributors": {
                "nodes": [
                    "kdickerson"
                ]
            },
            "nameWithOwner": "django-compressor/django-compressor"
        },
        "djsegal/JuliaPackages.jl": {
            "labContributors": {
                "nodes": [
                    "sbromberger"
                ]
            },
            "nameWithOwner": "djsegal/JuliaPackages.jl"
        },
        "docksal/addons": {
            "labContributors": {
                "nodes": [
                    "shelane"
                ]
            },
            "nameWithOwner": "docksal/addons"
        },
        "docksal/blt-docksal": {
            "labContributors": {
                "nodes": [
                    "shelane"
                ]
            },
            "nameWithOwner": "docksal/blt-docksal"
        },
        "docksal/boilerplate-backdrop": {
            "labContributors": {
                "nodes": [
                    "shelane"
                ]
            },
            "nameWithOwner": "docksal/boilerplate-backdrop"
        },
        "docksal/boilerplate-bedrock": {
            "labContributors": {
                "nodes": [
                    "shelane"
                ]
            },
            "nameWithOwner": "docksal/boilerplate-bedrock"
        },
        "docksal/boilerplate-drupal7": {
            "labContributors": {
                "nodes": [
                    "shelane"
                ]
            },
            "nameWithOwner": "docksal/boilerplate-drupal7"
        },
        "docksal/boilerplate-drupal7-advanced": {
            "labContributors": {
                "nodes": [
                    "shelane"
                ]
            },
            "nameWithOwner": "docksal/boilerplate-drupal7-advanced"
        },
        "docksal/boilerplate-drupal8": {
            "labContributors": {
                "nodes": [
                    "shelane"
                ]
            },
            "nameWithOwner": "docksal/boilerplate-drupal8"
        },
        "docksal/boilerplate-drupal8-blt": {
            "labContributors": {
                "nodes": [
                    "shelane"
                ]
            },
            "nameWithOwner": "docksal/boilerplate-drupal8-blt"
        },
        "docksal/boilerplate-drupal8-composer": {
            "labContributors": {
                "nodes": [
                    "shelane"
                ]
            },
            "nameWithOwner": "docksal/boilerplate-drupal8-composer"
        },
        "docksal/boilerplate-magento": {
            "labContributors": {
                "nodes": [
                    "shelane"
                ]
            },
            "nameWithOwner": "docksal/boilerplate-magento"
        },
        "docksal/boilerplate-magento-demo": {
            "labContributors": {
                "nodes": [
                    "shelane"
                ]
            },
            "nameWithOwner": "docksal/boilerplate-magento-demo"
        },
        "docksal/boilerplate-wordpress": {
            "labContributors": {
                "nodes": [
                    "shelane"
                ]
            },
            "nameWithOwner": "docksal/boilerplate-wordpress"
        },
        "docksal/ci-agent": {
            "labContributors": {
                "nodes": [
                    "shelane"
                ]
            },
            "nameWithOwner": "docksal/ci-agent"
        },
        "docksal/docksal": {
            "labContributors": {
                "nodes": [
                    "shelane"
                ]
            },
            "nameWithOwner": "docksal/docksal"
        },
        "docksal/docksal.io": {
            "labContributors": {
                "nodes": [
                    "shelane"
                ]
            },
            "nameWithOwner": "docksal/docksal.io"
        },
        "docksal/service-cli": {
            "labContributors": {
                "nodes": [
                    "shelane"
                ]
            },
            "nameWithOwner": "docksal/service-cli"
        },
        "docksal/service-mysql": {
            "labContributors": {
                "nodes": [
                    "shelane"
                ]
            },
            "nameWithOwner": "docksal/service-mysql"
        },
        "docksal/service-vhost-proxy": {
            "labContributors": {
                "nodes": [
                    "shelane"
                ]
            },
            "nameWithOwner": "docksal/service-vhost-proxy"
        },
        "dvidelabs/flatcc": {
            "labContributors": {
                "nodes": [
                    "tonyhutter"
                ]
            },
            "nameWithOwner": "dvidelabs/flatcc"
        },
        "dyninst/dyninst": {
            "labContributors": {
                "nodes": [
                    "mplegendre"
                ]
            },
            "nameWithOwner": "dyninst/dyninst"
        },
        "ecp-ci/ecp-ci.github.io": {
            "labContributors": {
                "nodes": [
                    "markcmiller86"
                ]
            },
            "nameWithOwner": "ecp-ci/ecp-ci.github.io"
        },
        "ecp-ci/initial-ci-example": {
            "labContributors": {
                "nodes": [
                    "markcmiller86"
                ]
            },
            "nameWithOwner": "ecp-ci/initial-ci-example"
        },
        "eddie-c-davis/gt4py": {
            "labContributors": {
                "nodes": [
                    "jdahm"
                ]
            },
            "nameWithOwner": "eddie-c-davis/gt4py"
        },
        "eigs/EVSL": {
            "labContributors": {
                "nodes": [
                    "liruipeng"
                ]
            },
            "nameWithOwner": "eigs/EVSL"
        },
        "emacs-lsp/dap-mode": {
            "labContributors": {
                "nodes": [
                    "goxberry"
                ]
            },
            "nameWithOwner": "emacs-lsp/dap-mode"
        },
        "emeryberger/CSrankings": {
            "labContributors": {
                "nodes": [
                    "bhatele"
                ]
            },
            "nameWithOwner": "emeryberger/CSrankings"
        },
        "epizon-project/Fenix": {
            "labContributors": {
                "nodes": [
                    "keitat"
                ]
            },
            "nameWithOwner": "epizon-project/Fenix"
        },
        "equinor/seismic-zfp": {
            "labContributors": {
                "nodes": [
                    "lindstro"
                ]
            },
            "nameWithOwner": "equinor/seismic-zfp"
        },
        "eth-cscs/sarus": {
            "labContributors": {
                "nodes": [
                    "jdahm"
                ]
            },
            "nameWithOwner": "eth-cscs/sarus"
        },
        "exercism/go": {
            "labContributors": {
                "nodes": [
                    "sbromberger"
                ]
            },
            "nameWithOwner": "exercism/go"
        },
        "fish-shell/fish-site": {
            "labContributors": {
                "nodes": [
                    "nightlark"
                ]
            },
            "nameWithOwner": "fish-shell/fish-site"
        },
        "flairNLP/flair": {
            "labContributors": {
                "nodes": [
                    "tjchambers32"
                ]
            },
            "nameWithOwner": "flairNLP/flair"
        },
        "flatsiedatsie/webthings-network-presence-detection": {
            "labContributors": {
                "nodes": [
                    "kdickerson"
                ]
            },
            "nameWithOwner": "flatsiedatsie/webthings-network-presence-detection"
        },
        "forsyth2/lbann": {
            "labContributors": {
                "nodes": [
                    "benson31"
                ]
            },
            "nameWithOwner": "forsyth2/lbann"
        },
        "freeCompilerCamp/freecompilercamp.github.io": {
            "labContributors": {
                "nodes": [
                    "chunhualiao"
                ]
            },
            "nameWithOwner": "freeCompilerCamp/freecompilercamp.github.io"
        },
        "freetonik/MPI-life": {
            "labContributors": {
                "nodes": [
                    "javawolfpack"
                ]
            },
            "nameWithOwner": "freetonik/MPI-life"
        },
        "garlick/brewcop": {
            "labContributors": {
                "nodes": [
                    "SteVwonder"
                ]
            },
            "nameWithOwner": "garlick/brewcop"
        },
        "genovese/win-switch": {
            "labContributors": {
                "nodes": [
                    "gonsie"
                ]
            },
            "nameWithOwner": "genovese/win-switch"
        },
        "geodynamics/sw4lite": {
            "labContributors": {
                "nodes": [
                    "bjorn2"
                ]
            },
            "nameWithOwner": "geodynamics/sw4lite"
        },
        "geopm/geopm": {
            "labContributors": {
                "nodes": [
                    "amarathe84",
                    "rountree",
                    "slabasan"
                ]
            },
            "nameWithOwner": "geopm/geopm"
        },
        "gleisonsdm/AutoParBench": {
            "labContributors": {
                "nodes": [
                    "chunhualiao"
                ]
            },
            "nameWithOwner": "gleisonsdm/AutoParBench"
        },
        "gleisonsdm/OpenMP_benchmarks": {
            "labContributors": {
                "nodes": [
                    "chunhualiao"
                ]
            },
            "nameWithOwner": "gleisonsdm/OpenMP_benchmarks"
        },
        "gnunn1/tilix": {
            "labContributors": {
                "nodes": [
                    "correaa"
                ]
            },
            "nameWithOwner": "gnunn1/tilix"
        },
        "gohugoio/hugoThemes": {
            "labContributors": {
                "nodes": [
                    "jdahm"
                ]
            },
            "nameWithOwner": "gohugoio/hugoThemes"
        },
        "golang/go": {
            "labContributors": {
                "nodes": [
                    "sbromberger"
                ]
            },
            "nameWithOwner": "golang/go"
        },
        "google/go-github": {
            "labContributors": {
                "nodes": [
                    "nightlark"
                ]
            },
            "nameWithOwner": "google/go-github"
        },
        "google/sanitizers": {
            "labContributors": {
                "nodes": [
                    "adayton1"
                ]
            },
            "nameWithOwner": "google/sanitizers"
        },
        "guille-rochelle/guille-rochelle.github.io": {
            "labContributors": {
                "nodes": [
                    "trappitsch"
                ]
            },
            "nameWithOwner": "guille-rochelle/guille-rochelle.github.io"
        },
        "gulrak/filesystem": {
            "labContributors": {
                "nodes": [
                    "nightlark",
                    "phlptp"
                ]
            },
            "nameWithOwner": "gulrak/filesystem"
        },
        "hdc-arizona/computing-graphs-corpus": {
            "labContributors": {
                "nodes": [
                    "kisaacs"
                ]
            },
            "nameWithOwner": "hdc-arizona/computing-graphs-corpus"
        },
        "hdc-arizona/graph-drawing-libraries-primer": {
            "labContributors": {
                "nodes": [
                    "kisaacs"
                ]
            },
            "nameWithOwner": "hdc-arizona/graph-drawing-libraries-primer"
        },
        "hdc-arizona/hdc-arizona.github.io": {
            "labContributors": {
                "nodes": [
                    "kisaacs"
                ]
            },
            "nameWithOwner": "hdc-arizona/hdc-arizona.github.io"
        },
        "hdc-arizona/traveler-gantt": {
            "labContributors": {
                "nodes": [
                    "kisaacs"
                ]
            },
            "nameWithOwner": "hdc-arizona/traveler-gantt"
        },
        "hdc-arizona/traveler-integrated": {
            "labContributors": {
                "nodes": [
                    "kisaacs"
                ]
            },
            "nameWithOwner": "hdc-arizona/traveler-integrated"
        },
        "hfinkel/cxx_interfaces_paper": {
            "labContributors": {
                "nodes": [
                    "trws"
                ]
            },
            "nameWithOwner": "hfinkel/cxx_interfaces_paper"
        },
        "hishamhm/f-strings": {
            "labContributors": {
                "nodes": [
                    "lee-busby"
                ]
            },
            "nameWithOwner": "hishamhm/f-strings"
        },
        "hpc/libcircle": {
            "labContributors": {
                "nodes": [
                    "adammoody",
                    "gonsie"
                ]
            },
            "nameWithOwner": "hpc/libcircle"
        },
        "hpc/pavilion2": {
            "labContributors": {
                "nodes": [
                    "BenCasses"
                ]
            },
            "nameWithOwner": "hpc/pavilion2"
        },
        "hpcbootcamp/hpcbootcamp": {
            "labContributors": {
                "nodes": [
                    "bhatele"
                ]
            },
            "nameWithOwner": "hpcbootcamp/hpcbootcamp"
        },
        "hpcg-benchmark/hpcg": {
            "labContributors": {
                "nodes": [
                    "ikarlin"
                ]
            },
            "nameWithOwner": "hpcg-benchmark/hpcg"
        },
        "hpcgroup/bib": {
            "labContributors": {
                "nodes": [
                    "bhatele"
                ]
            },
            "nameWithOwner": "hpcgroup/bib"
        },
        "hust-workshop/organizer-notes": {
            "labContributors": {
                "nodes": [
                    "gonsie"
                ]
            },
            "nameWithOwner": "hust-workshop/organizer-notes"
        },
        "hypar/hypar.github.io": {
            "labContributors": {
                "nodes": [
                    "debog"
                ]
            },
            "nameWithOwner": "hypar/hypar.github.io"
        },
        "ieee-vgtc/ieeevis.org": {
            "labContributors": {
                "nodes": [
                    "lindstro"
                ]
            },
            "nameWithOwner": "ieee-vgtc/ieeevis.org"
        },
        "imneme/pcg-cpp": {
            "labContributors": {
                "nodes": [
                    "xavierandrade"
                ]
            },
            "nameWithOwner": "imneme/pcg-cpp"
        },
        "intel/QAT_Engine": {
            "labContributors": {
                "nodes": [
                    "tonyhutter"
                ]
            },
            "nameWithOwner": "intel/QAT_Engine"
        },
        "jmikeowen/spheral": {
            "labContributors": {
                "nodes": [
                    "mdavis36"
                ]
            },
            "nameWithOwner": "jmikeowen/spheral"
        },
        "jmunixusers/constitution": {
            "labContributors": {
                "nodes": [
                    "lam2mo"
                ]
            },
            "nameWithOwner": "jmunixusers/constitution"
        },
        "jmunixusers/cs-vm-build": {
            "labContributors": {
                "nodes": [
                    "lam2mo"
                ]
            },
            "nameWithOwner": "jmunixusers/cs-vm-build"
        },
        "jmunixusers/history": {
            "labContributors": {
                "nodes": [
                    "lam2mo"
                ]
            },
            "nameWithOwner": "jmunixusers/history"
        },
        "jmunixusers/presentations": {
            "labContributors": {
                "nodes": [
                    "lam2mo"
                ]
            },
            "nameWithOwner": "jmunixusers/presentations"
        },
        "joaomlneto/cpds-heat": {
            "labContributors": {
                "nodes": [
                    "markcmiller86"
                ]
            },
            "nameWithOwner": "joaomlneto/cpds-heat"
        },
        "jonathanabennett/jonathanabennett.github.io": {
            "labContributors": {
                "nodes": [
                    "gonsie"
                ]
            },
            "nameWithOwner": "jonathanabennett/jonathanabennett.github.io"
        },
        "jopohl/urh": {
            "labContributors": {
                "nodes": [
                    "nightlark"
                ]
            },
            "nameWithOwner": "jopohl/urh"
        },
        "jorgenschaefer/elpy": {
            "labContributors": {
                "nodes": [
                    "dstrozzi"
                ]
            },
            "nameWithOwner": "jorgenschaefer/elpy"
        },
        "jorgenschaefer/pyvenv": {
            "labContributors": {
                "nodes": [
                    "dstrozzi"
                ]
            },
            "nameWithOwner": "jorgenschaefer/pyvenv"
        },
        "jpype-project/jpype": {
            "labContributors": {
                "nodes": [
                    "Thrameos",
                    "clanker",
                    "mattooca"
                ]
            },
            "nameWithOwner": "jpype-project/jpype"
        },
        "jsvine/markovify": {
            "labContributors": {
                "nodes": [
                    "ben-bay"
                ]
            },
            "nameWithOwner": "jsvine/markovify"
        },
        "jupyter/notebook": {
            "labContributors": {
                "nodes": [
                    "carolzhou"
                ]
            },
            "nameWithOwner": "jupyter/notebook"
        },
        "jupyterhub/jupyterhub": {
            "labContributors": {
                "nodes": [
                    "cyrush",
                    "tgmachina"
                ]
            },
            "nameWithOwner": "jupyterhub/jupyterhub"
        },
        "kdheepak/helics-builder": {
            "labContributors": {
                "nodes": [
                    "nightlark",
                    "phlptp"
                ]
            },
            "nameWithOwner": "kdheepak/helics-builder"
        },
        "khuck/xpress-apex": {
            "labContributors": {
                "nodes": [
                    "kisaacs"
                ]
            },
            "nameWithOwner": "khuck/xpress-apex"
        },
        "kokkos/kokkos": {
            "labContributors": {
                "nodes": [
                    "DavidPoliakoff",
                    "keitat",
                    "pguthrey",
                    "trws"
                ]
            },
            "nameWithOwner": "kokkos/kokkos"
        },
        "kokkos/kokkos-kernels": {
            "labContributors": {
                "nodes": [
                    "DavidPoliakoff"
                ]
            },
            "nameWithOwner": "kokkos/kokkos-kernels"
        },
        "kokkos/kokkos-spack": {
            "labContributors": {
                "nodes": [
                    "DavidPoliakoff"
                ]
            },
            "nameWithOwner": "kokkos/kokkos-spack"
        },
        "kokkos/kokkos-tools": {
            "labContributors": {
                "nodes": [
                    "DavidPoliakoff",
                    "daboehme"
                ]
            },
            "nameWithOwner": "kokkos/kokkos-tools"
        },
        "kokkos/kokkos-tutorials": {
            "labContributors": {
                "nodes": [
                    "DavidPoliakoff"
                ]
            },
            "nameWithOwner": "kokkos/kokkos-tutorials"
        },
        "lanl-preteam/pavilion2": {
            "labContributors": {
                "nodes": [
                    "BenCasses"
                ]
            },
            "nameWithOwner": "lanl-preteam/pavilion2"
        },
        "lanl/bml": {
            "labContributors": {
                "nodes": [
                    "oseikuffuor1"
                ]
            },
            "nameWithOwner": "lanl/bml"
        },
        "laristra/tangram": {
            "labContributors": {
                "nodes": [
                    "wnissen"
                ]
            },
            "nameWithOwner": "laristra/tangram"
        },
        "laughingman7743/PyAthenaJDBC": {
            "labContributors": {
                "nodes": [
                    "Thrameos"
                ]
            },
            "nameWithOwner": "laughingman7743/PyAthenaJDBC"
        },
        "lc-bot/llnl.github.io-actions": {
            "labContributors": {
                "nodes": [
                    "LRWeber"
                ]
            },
            "nameWithOwner": "lc-bot/llnl.github.io-actions"
        },
        "libocca/occa": {
            "labContributors": {
                "nodes": [
                    "artv3"
                ]
            },
            "nameWithOwner": "libocca/occa"
        },
        "lpeabody/Metis": {
            "labContributors": {
                "nodes": [
                    "shelane"
                ]
            },
            "nameWithOwner": "lpeabody/Metis"
        },
        "lukasa1993/scp-client": {
            "labContributors": {
                "nodes": [
                    "gonsie"
                ]
            },
            "nameWithOwner": "lukasa1993/scp-client"
        },
        "mame/quine-relay": {
            "labContributors": {
                "nodes": [
                    "lam2mo"
                ]
            },
            "nameWithOwner": "mame/quine-relay"
        },
        "mapheysc/hanabi-api": {
            "labContributors": {
                "nodes": [
                    "joe-eklund"
                ]
            },
            "nameWithOwner": "mapheysc/hanabi-api"
        },
        "mapheysc/hanabi-engine": {
            "labContributors": {
                "nodes": [
                    "samueldeklund"
                ]
            },
            "nameWithOwner": "mapheysc/hanabi-engine"
        },
        "marklogic/marklogic-data-hub": {
            "labContributors": {
                "nodes": [
                    "tjchambers32"
                ]
            },
            "nameWithOwner": "marklogic/marklogic-data-hub"
        },
        "mattgodbolt/compiler-explorer": {
            "labContributors": {
                "nodes": [
                    "correaa"
                ]
            },
            "nameWithOwner": "mattgodbolt/compiler-explorer"
        },
        "matthewpdias/chico-acm.com": {
            "labContributors": {
                "nodes": [
                    "javawolfpack"
                ]
            },
            "nameWithOwner": "matthewpdias/chico-acm.com"
        },
        "maxdeliso/micron": {
            "labContributors": {
                "nodes": [
                    "jdahm"
                ]
            },
            "nameWithOwner": "maxdeliso/micron"
        },
        "mclarsen/ascent_chapter": {
            "labContributors": {
                "nodes": [
                    "brugger1",
                    "cyrush",
                    "slabasan"
                ]
            },
            "nameWithOwner": "mclarsen/ascent_chapter"
        },
        "mcneish1/Aluminum": {
            "labContributors": {
                "nodes": [
                    "benson31"
                ]
            },
            "nameWithOwner": "mcneish1/Aluminum"
        },
        "melowntech/buildsys-cmake": {
            "labContributors": {
                "nodes": [
                    "jakubcerveny"
                ]
            },
            "nameWithOwner": "melowntech/buildsys-cmake"
        },
        "melowntech/libimgproc": {
            "labContributors": {
                "nodes": [
                    "jakubcerveny"
                ]
            },
            "nameWithOwner": "melowntech/libimgproc"
        },
        "mercury-hpc/mercury": {
            "labContributors": {
                "nodes": [
                    "CamStan",
                    "tonyhutter"
                ]
            },
            "nameWithOwner": "mercury-hpc/mercury"
        },
        "metakirby5/codi.vim": {
            "labContributors": {
                "nodes": [
                    "sbromberger"
                ]
            },
            "nameWithOwner": "metakirby5/codi.vim"
        },
        "micheletufano/DeepMutation": {
            "labContributors": {
                "nodes": [
                    "jskimko"
                ]
            },
            "nameWithOwner": "micheletufano/DeepMutation"
        },
        "mknejp/vmcontainer": {
            "labContributors": {
                "nodes": [
                    "correaa"
                ]
            },
            "nameWithOwner": "mknejp/vmcontainer"
        },
        "mozilla-iot/gateway": {
            "labContributors": {
                "nodes": [
                    "kdickerson"
                ]
            },
            "nameWithOwner": "mozilla-iot/gateway"
        },
        "mozilla-iot/tplink-adapter": {
            "labContributors": {
                "nodes": [
                    "kdickerson"
                ]
            },
            "nameWithOwner": "mozilla-iot/tplink-adapter"
        },
        "mpSchrader/gym-sokoban": {
            "labContributors": {
                "nodes": [
                    "ben-bay"
                ]
            },
            "nameWithOwner": "mpSchrader/gym-sokoban"
        },
        "mpi-forum/mpi-forum.github.io": {
            "labContributors": {
                "nodes": [
                    "schulzm"
                ]
            },
            "nameWithOwner": "mpi-forum/mpi-forum.github.io"
        },
        "mpi-forum/mpi-issues": {
            "labContributors": {
                "nodes": [
                    "schulzm"
                ]
            },
            "nameWithOwner": "mpi-forum/mpi-issues"
        },
        "mpiwg-ft/ft-issues": {
            "labContributors": {
                "nodes": [
                    "ilagunap"
                ]
            },
            "nameWithOwner": "mpiwg-ft/ft-issues"
        },
        "msys2/MINGW-packages": {
            "labContributors": {
                "nodes": [
                    "phlptp"
                ]
            },
            "nameWithOwner": "msys2/MINGW-packages"
        },
        "mucs420f19/GWCA": {
            "labContributors": {
                "nodes": [
                    "willkill07"
                ]
            },
            "nameWithOwner": "mucs420f19/GWCA"
        },
        "mucs420f19/Hercules": {
            "labContributors": {
                "nodes": [
                    "willkill07"
                ]
            },
            "nameWithOwner": "mucs420f19/Hercules"
        },
        "mucs420f19/HyperTextAssassins": {
            "labContributors": {
                "nodes": [
                    "willkill07"
                ]
            },
            "nameWithOwner": "mucs420f19/HyperTextAssassins"
        },
        "mucs420f19/JJARS": {
            "labContributors": {
                "nodes": [
                    "willkill07"
                ]
            },
            "nameWithOwner": "mucs420f19/JJARS"
        },
        "mucs420f19/MMouseLLC": {
            "labContributors": {
                "nodes": [
                    "willkill07"
                ]
            },
            "nameWithOwner": "mucs420f19/MMouseLLC"
        },
        "mucsci-students/2020sp-420-CowboyEmoji7": {
            "labContributors": {
                "nodes": [
                    "willkill07"
                ]
            },
            "nameWithOwner": "mucsci-students/2020sp-420-CowboyEmoji7"
        },
        "mucsci-students/2020sp-420-ProjectZero": {
            "labContributors": {
                "nodes": [
                    "willkill07"
                ]
            },
            "nameWithOwner": "mucsci-students/2020sp-420-ProjectZero"
        },
        "mucsci-students/2020sp-420-TeamAwesome": {
            "labContributors": {
                "nodes": [
                    "willkill07"
                ]
            },
            "nameWithOwner": "mucsci-students/2020sp-420-TeamAwesome"
        },
        "mucsci-students/2020sp-420-WebWizards": {
            "labContributors": {
                "nodes": [
                    "willkill07"
                ]
            },
            "nameWithOwner": "mucsci-students/2020sp-420-WebWizards"
        },
        "mucsci-students/2020sp-420-ascii_shrug": {
            "labContributors": {
                "nodes": [
                    "willkill07"
                ]
            },
            "nameWithOwner": "mucsci-students/2020sp-420-ascii_shrug"
        },
        "mwest1066/randexam": {
            "labContributors": {
                "nodes": [
                    "joshuata"
                ]
            },
            "nameWithOwner": "mwest1066/randexam"
        },
        "naoyam/lbann": {
            "labContributors": {
                "nodes": [
                    "bvanessen"
                ]
            },
            "nameWithOwner": "naoyam/lbann"
        },
        "napalm00/PlaceInRedStandalone": {
            "labContributors": {
                "nodes": [
                    "aaroncblack"
                ]
            },
            "nameWithOwner": "napalm00/PlaceInRedStandalone"
        },
        "neely4/llnl.github.io": {
            "labContributors": {
                "nodes": [
                    "adrienbernede"
                ]
            },
            "nameWithOwner": "neely4/llnl.github.io"
        },
        "neomake/neomake": {
            "labContributors": {
                "nodes": [
                    "sbromberger"
                ]
            },
            "nameWithOwner": "neomake/neomake"
        },
        "newren/git-filter-repo": {
            "labContributors": {
                "nodes": [
                    "adrienbernede"
                ]
            },
            "nameWithOwner": "newren/git-filter-repo"
        },
        "ngbrenda/FOQUS": {
            "labContributors": {
                "nodes": [
                    "sotorrio1"
                ]
            },
            "nameWithOwner": "ngbrenda/FOQUS"
        },
        "niklasvh/html2canvas": {
            "labContributors": {
                "nodes": [
                    "tjchambers32"
                ]
            },
            "nameWithOwner": "niklasvh/html2canvas"
        },
        "ninja-build/ninja": {
            "labContributors": {
                "nodes": [
                    "nightlark"
                ]
            },
            "nameWithOwner": "ninja-build/ninja"
        },
        "nsnam/ns-3-dev-git": {
            "labContributors": {
                "nodes": [
                    "nightlark"
                ]
            },
            "nameWithOwner": "nsnam/ns-3-dev-git"
        },
        "octachrome/treason": {
            "labContributors": {
                "nodes": [
                    "joe-eklund"
                ]
            },
            "nameWithOwner": "octachrome/treason"
        },
        "octokit/octokit.rb": {
            "labContributors": {
                "nodes": [
                    "tgmachina"
                ]
            },
            "nameWithOwner": "octokit/octokit.rb"
        },
        "octopus/octopus": {
            "labContributors": {
                "nodes": [
                    "xavierandrade"
                ]
            },
            "nameWithOwner": "octopus/octopus"
        },
        "onqtam/ucm": {
            "labContributors": {
                "nodes": [
                    "nightlark"
                ]
            },
            "nameWithOwner": "onqtam/ucm"
        },
        "open-mpi/mtt": {
            "labContributors": {
                "nodes": [
                    "dsikich"
                ]
            },
            "nameWithOwner": "open-mpi/mtt"
        },
        "open-mpi/ompi": {
            "labContributors": {
                "nodes": [
                    "SteVwonder"
                ]
            },
            "nameWithOwner": "open-mpi/ompi"
        },
        "openpmix/openpmix": {
            "labContributors": {
                "nodes": [
                    "SteVwonder",
                    "dsikich"
                ]
            },
            "nameWithOwner": "openpmix/openpmix"
        },
        "openpmix/pmi-shim": {
            "labContributors": {
                "nodes": [
                    "SteVwonder"
                ]
            },
            "nameWithOwner": "openpmix/pmi-shim"
        },
        "openpmix/pmix-tests": {
            "labContributors": {
                "nodes": [
                    "dsikich"
                ]
            },
            "nameWithOwner": "openpmix/pmix-tests"
        },
        "ouankou/rose-demo-docker": {
            "labContributors": {
                "nodes": [
                    "chunhualiao"
                ]
            },
            "nameWithOwner": "ouankou/rose-demo-docker"
        },
        "overleaf/web": {
            "labContributors": {
                "nodes": [
                    "samusangio"
                ]
            },
            "nameWithOwner": "overleaf/web"
        },
        "ovis-hpc/ovis": {
            "labContributors": {
                "nodes": [
                    "morrone"
                ]
            },
            "nameWithOwner": "ovis-hpc/ovis"
        },
        "oyamay/lbann": {
            "labContributors": {
                "nodes": [
                    "naoyam"
                ]
            },
            "nameWithOwner": "oyamay/lbann"
        },
        "paralab/Dendro-KT": {
            "labContributors": {
                "nodes": [
                    "starintheuniverse"
                ]
            },
            "nameWithOwner": "paralab/Dendro-KT"
        },
        "passlab/ompparser": {
            "labContributors": {
                "nodes": [
                    "chunhualiao"
                ]
            },
            "nameWithOwner": "passlab/ompparser"
        },
        "pelson/jpype": {
            "labContributors": {
                "nodes": [
                    "Thrameos"
                ]
            },
            "nameWithOwner": "pelson/jpype"
        },
        "phlptp/jsoncpp": {
            "labContributors": {
                "nodes": [
                    "nightlark"
                ]
            },
            "nameWithOwner": "phlptp/jsoncpp"
        },
        "phusion/holy-build-box": {
            "labContributors": {
                "nodes": [
                    "nightlark"
                ]
            },
            "nameWithOwner": "phusion/holy-build-box"
        },
        "play-with-docker/play-with-docker": {
            "labContributors": {
                "nodes": [
                    "chunhualiao"
                ]
            },
            "nameWithOwner": "play-with-docker/play-with-docker"
        },
        "play-with-docker/play-with-docker.github.io": {
            "labContributors": {
                "nodes": [
                    "chunhualiao"
                ]
            },
            "nameWithOwner": "play-with-docker/play-with-docker.github.io"
        },
        "pmix/governance": {
            "labContributors": {
                "nodes": [
                    "SteVwonder",
                    "kathrynmohror"
                ]
            },
            "nameWithOwner": "pmix/governance"
        },
        "pmix/pmix-standard": {
            "labContributors": {
                "nodes": [
                    "SteVwonder",
                    "kathrynmohror"
                ]
            },
            "nameWithOwner": "pmix/pmix-standard"
        },
        "pmix/pmix.github.io": {
            "labContributors": {
                "nodes": [
                    "SteVwonder"
                ]
            },
            "nameWithOwner": "pmix/pmix.github.io"
        },
        "pqrs-org/Karabiner-Elements": {
            "labContributors": {
                "nodes": [
                    "dstrozzi"
                ]
            },
            "nameWithOwner": "pqrs-org/Karabiner-Elements"
        },
        "protools19/protools19.github.io": {
            "labContributors": {
                "nodes": [
                    "bhatele",
                    "daboehme"
                ]
            },
            "nameWithOwner": "protools19/protools19.github.io"
        },
        "protools20/protools20.github.io": {
            "labContributors": {
                "nodes": [
                    "bhatele"
                ]
            },
            "nameWithOwner": "protools20/protools20.github.io"
        },
        "pybind/pybind11": {
            "labContributors": {
                "nodes": [
                    "jskimko",
                    "rfhaque"
                ]
            },
            "nameWithOwner": "pybind/pybind11"
        },
        "pyenv/pyenv": {
            "labContributors": {
                "nodes": [
                    "lee218llnl"
                ]
            },
            "nameWithOwner": "pyenv/pyenv"
        },
        "pypa/pypi-support": {
            "labContributors": {
                "nodes": [
                    "ben-bay",
                    "lindstro"
                ]
            },
            "nameWithOwner": "pypa/pypi-support"
        },
        "pytest-dev/pytest": {
            "labContributors": {
                "nodes": [
                    "nightlark"
                ]
            },
            "nameWithOwner": "pytest-dev/pytest"
        },
        "pythonic-emacs/blacken": {
            "labContributors": {
                "nodes": [
                    "tgamblin"
                ]
            },
            "nameWithOwner": "pythonic-emacs/blacken"
        },
        "pytorch/pytorch": {
            "labContributors": {
                "nodes": [
                    "timmoon10"
                ]
            },
            "nameWithOwner": "pytorch/pytorch"
        },
        "ralna/spral": {
            "labContributors": {
                "nodes": [
                    "pelesh"
                ]
            },
            "nameWithOwner": "ralna/spral"
        },
        "raspberrypi/linux": {
            "labContributors": {
                "nodes": [
                    "sbromberger"
                ]
            },
            "nameWithOwner": "raspberrypi/linux"
        },
        "raspberrypi/userland": {
            "labContributors": {
                "nodes": [
                    "sbromberger"
                ]
            },
            "nameWithOwner": "raspberrypi/userland"
        },
        "readthedocs/readthedocs.org": {
            "labContributors": {
                "nodes": [
                    "markcmiller86",
                    "tgamblin"
                ]
            },
            "nameWithOwner": "readthedocs/readthedocs.org"
        },
        "revivepres/rockx": {
            "labContributors": {
                "nodes": [
                    "johnlee"
                ]
            },
            "nameWithOwner": "revivepres/rockx"
        },
        "rgbkrk/atom-script": {
            "labContributors": {
                "nodes": [
                    "trappitsch"
                ]
            },
            "nameWithOwner": "rgbkrk/atom-script"
        },
        "ridiculousfish/libdivide": {
            "labContributors": {
                "nodes": [
                    "nightlark"
                ]
            },
            "nameWithOwner": "ridiculousfish/libdivide"
        },
        "riyamarabo/IBMHackathon": {
            "labContributors": {
                "nodes": [
                    "ymubarka"
                ]
            },
            "nameWithOwner": "riyamarabo/IBMHackathon"
        },
        "rpm-software-management/mock": {
            "labContributors": {
                "nodes": [
                    "tonyhutter"
                ]
            },
            "nameWithOwner": "rpm-software-management/mock"
        },
        "rquey/neper": {
            "labContributors": {
                "nodes": [
                    "rcarson3"
                ]
            },
            "nameWithOwner": "rquey/neper"
        },
        "rsearles35/Spark-Plus-Accelerator": {
            "labContributors": {
                "nodes": [
                    "SteVwonder"
                ]
            },
            "nameWithOwner": "rsearles35/Spark-Plus-Accelerator"
        },
        "rseng/awesome-rseng": {
            "labContributors": {
                "nodes": [
                    "adrienbernede"
                ]
            },
            "nameWithOwner": "rseng/awesome-rseng"
        },
        "rust-lang/rustup": {
            "labContributors": {
                "nodes": [
                    "nightlark"
                ]
            },
            "nameWithOwner": "rust-lang/rustup"
        },
        "rust-ndarray/ndarray": {
            "labContributors": {
                "nodes": [
                    "rcarson3"
                ]
            },
            "nameWithOwner": "rust-ndarray/ndarray"
        },
        "rwols/yaml-archive": {
            "labContributors": {
                "nodes": [
                    "correaa"
                ]
            },
            "nameWithOwner": "rwols/yaml-archive"
        },
        "ryan-mast/ninja": {
            "labContributors": {
                "nodes": [
                    "nightlark"
                ]
            },
            "nameWithOwner": "ryan-mast/ninja"
        },
        "sci-visus/OpenVisus": {
            "labContributors": {
                "nodes": [
                    "ptbremer"
                ]
            },
            "nameWithOwner": "sci-visus/OpenVisus"
        },
        "sci-visus/ipyvisus": {
            "labContributors": {
                "nodes": [
                    "yarden-livnat"
                ]
            },
            "nameWithOwner": "sci-visus/ipyvisus"
        },
        "sonhte/ninja": {
            "labContributors": {
                "nodes": [
                    "nightlark"
                ]
            },
            "nameWithOwner": "sonhte/ninja"
        },
        "sosy-lab/benchexec": {
            "labContributors": {
                "nodes": [
                    "bquiring"
                ]
            },
            "nameWithOwner": "sosy-lab/benchexec"
        },
        "sosy-lab/sv-comp": {
            "labContributors": {
                "nodes": [
                    "bquiring"
                ]
            },
            "nameWithOwner": "sosy-lab/sv-comp"
        },
        "steven-lang-git/ChargeMeMobileApp": {
            "labContributors": {
                "nodes": [
                    "JazzyJas0911",
                    "angfl97"
                ]
            },
            "nameWithOwner": "steven-lang-git/ChargeMeMobileApp"
        },
        "swift-lang/swift-t": {
            "labContributors": {
                "nodes": [
                    "adammoody"
                ]
            },
            "nameWithOwner": "swift-lang/swift-t"
        },
        "swig/swig": {
            "labContributors": {
                "nodes": [
                    "nightlark"
                ]
            },
            "nameWithOwner": "swig/swig"
        },
        "taohexxx/lightline-buffer": {
            "labContributors": {
                "nodes": [
                    "sbromberger"
                ]
            },
            "nameWithOwner": "taohexxx/lightline-buffer"
        },
        "tcalmant/python-javaobj": {
            "labContributors": {
                "nodes": [
                    "Thrameos"
                ]
            },
            "nameWithOwner": "tcalmant/python-javaobj"
        },
        "tgamblin/review-request-action-test": {
            "labContributors": {
                "nodes": [
                    "mclarsen"
                ]
            },
            "nameWithOwner": "tgamblin/review-request-action-test"
        },
        "threelittlemonkeys/lstm-crf-pytorch": {
            "labContributors": {
                "nodes": [
                    "ben-bay"
                ]
            },
            "nameWithOwner": "threelittlemonkeys/lstm-crf-pytorch"
        },
        "thrust/thrust": {
            "labContributors": {
                "nodes": [
                    "correaa",
                    "liruipeng"
                ]
            },
            "nameWithOwner": "thrust/thrust"
        },
        "tiangolo/fastapi": {
            "labContributors": {
                "nodes": [
                    "joe-eklund"
                ]
            },
            "nameWithOwner": "tiangolo/fastapi"
        },
        "tidyverse/dplyr": {
            "labContributors": {
                "nodes": [
                    "clanker"
                ]
            },
            "nameWithOwner": "tidyverse/dplyr"
        },
        "timlrx/graph-benchmarks": {
            "labContributors": {
                "nodes": [
                    "sbromberger"
                ]
            },
            "nameWithOwner": "timlrx/graph-benchmarks"
        },
        "titu1994/neural-architecture-search": {
            "labContributors": {
                "nodes": [
                    "brendenpetersen"
                ]
            },
            "nameWithOwner": "titu1994/neural-architecture-search"
        },
        "tmux/tmux": {
            "labContributors": {
                "nodes": [
                    "rountree"
                ]
            },
            "nameWithOwner": "tmux/tmux"
        },
        "trilinos/Trilinos": {
            "labContributors": {
                "nodes": [
                    "keitat"
                ]
            },
            "nameWithOwner": "trilinos/Trilinos"
        },
        "trilinos/trilinos.github.io": {
            "labContributors": {
                "nodes": [
                    "keitat"
                ]
            },
            "nameWithOwner": "trilinos/trilinos.github.io"
        },
        "tschuchortdev/cmake_git_clone": {
            "labContributors": {
                "nodes": [
                    "nightlark",
                    "phlptp"
                ]
            },
            "nameWithOwner": "tschuchortdev/cmake_git_clone"
        },
        "twicki/dawn": {
            "labContributors": {
                "nodes": [
                    "jdahm"
                ]
            },
            "nameWithOwner": "twicki/dawn"
        },
        "twicki/gt4py": {
            "labContributors": {
                "nodes": [
                    "jdahm"
                ]
            },
            "nameWithOwner": "twicki/gt4py"
        },
        "twicki/gt4py2dawn": {
            "labContributors": {
                "nodes": [
                    "jdahm"
                ]
            },
            "nameWithOwner": "twicki/gt4py2dawn"
        },
        "typhonius/acquia_cli": {
            "labContributors": {
                "nodes": [
                    "shelane"
                ]
            },
            "nameWithOwner": "typhonius/acquia_cli"
        },
        "uacsc343spring2020/assignments": {
            "labContributors": {
                "nodes": [
                    "kisaacs"
                ]
            },
            "nameWithOwner": "uacsc343spring2020/assignments"
        },
        "uacsc343spring2020/ha2-base": {
            "labContributors": {
                "nodes": [
                    "kisaacs"
                ]
            },
            "nameWithOwner": "uacsc343spring2020/ha2-base"
        },
        "uacsc544fall2019/assignments": {
            "labContributors": {
                "nodes": [
                    "kisaacs"
                ]
            },
            "nameWithOwner": "uacsc544fall2019/assignments"
        },
        "uacsc544fall2019/ha1a-base": {
            "labContributors": {
                "nodes": [
                    "kisaacs"
                ]
            },
            "nameWithOwner": "uacsc544fall2019/ha1a-base"
        },
        "uacsc544fall2019/ha1b-base": {
            "labContributors": {
                "nodes": [
                    "kisaacs"
                ]
            },
            "nameWithOwner": "uacsc544fall2019/ha1b-base"
        },
        "uacsc544fall2019/ha2-base": {
            "labContributors": {
                "nodes": [
                    "kisaacs"
                ]
            },
            "nameWithOwner": "uacsc544fall2019/ha2-base"
        },
        "uacsc544fall2019/ha3-base": {
            "labContributors": {
                "nodes": [
                    "kisaacs"
                ]
            },
            "nameWithOwner": "uacsc544fall2019/ha3-base"
        },
        "uacsc544fall2019/pm1-base": {
            "labContributors": {
                "nodes": [
                    "kisaacs"
                ]
            },
            "nameWithOwner": "uacsc544fall2019/pm1-base"
        },
        "ucdchessai/chess-ai": {
            "labContributors": {
                "nodes": [
                    "zekemorton"
                ]
            },
            "nameWithOwner": "ucdchessai/chess-ai"
        },
        "ulule/limiter": {
            "labContributors": {
                "nodes": [
                    "angfl97"
                ]
            },
            "nameWithOwner": "ulule/limiter"
        },
        "uncrustify/uncrustify": {
            "labContributors": {
                "nodes": [
                    "rrsettgast"
                ]
            },
            "nameWithOwner": "uncrustify/uncrustify"
        },
        "v21/tracery": {
            "labContributors": {
                "nodes": [
                    "ben-bay"
                ]
            },
            "nameWithOwner": "v21/tracery"
        },
        "wrf-model/WRF": {
            "labContributors": {
                "nodes": [
                    "kalundquist"
                ]
            },
            "nameWithOwner": "wrf-model/WRF"
        },
        "xcat2/xcat-core": {
            "labContributors": {
                "nodes": [
                    "watson6282"
                ]
            },
            "nameWithOwner": "xcat2/xcat-core"
        },
        "xdesro/personalsit.es": {
            "labContributors": {
                "nodes": [
                    "gonsie"
                ]
            },
            "nameWithOwner": "xdesro/personalsit.es"
        },
        "xsdk-project/ATPESC2018HandsOnLessons": {
            "labContributors": {
                "nodes": [
                    "gonsie",
                    "markcmiller86"
                ]
            },
            "nameWithOwner": "xsdk-project/ATPESC2018HandsOnLessons"
        },
        "xsdk-project/IDEAS-ECP-QR-Landings": {
            "labContributors": {
                "nodes": [
                    "markcmiller86"
                ]
            },
            "nameWithOwner": "xsdk-project/IDEAS-ECP-QR-Landings"
        },
        "xsdk-project/MathPackagesTraining": {
            "labContributors": {
                "nodes": [
                    "markcmiller86"
                ]
            },
            "nameWithOwner": "xsdk-project/MathPackagesTraining"
        },
        "xsdk-project/xsdk-community-policies": {
            "labContributors": {
                "nodes": [
                    "acfisher",
                    "balos1",
                    "gardner48",
                    "osborn9",
                    "tzanio",
                    "ulrikeyang"
                ]
            },
            "nameWithOwner": "xsdk-project/xsdk-community-policies"
        },
        "xsdk-project/xsdk-examples": {
            "labContributors": {
                "nodes": [
                    "acfisher",
                    "balos1",
                    "keitat",
                    "osborn9",
                    "ulrikeyang"
                ]
            },
            "nameWithOwner": "xsdk-project/xsdk-examples"
        },
        "xsdk-project/xsdk-issues": {
            "labContributors": {
                "nodes": [
                    "acfisher",
                    "keitat"
                ]
            },
            "nameWithOwner": "xsdk-project/xsdk-issues"
        },
        "xsdk-project/xsdk-policy-compatibility": {
            "labContributors": {
                "nodes": [
                    "balos1",
                    "gardner48"
                ]
            },
            "nameWithOwner": "xsdk-project/xsdk-policy-compatibility"
        },
        "yixuan/spectra": {
            "labContributors": {
                "nodes": [
                    "jakubcerveny"
                ]
            },
            "nameWithOwner": "yixuan/spectra"
        },
        "zeromq/cppzmq": {
            "labContributors": {
                "nodes": [
                    "phlptp"
                ]
            },
            "nameWithOwner": "zeromq/cppzmq"
        },
        "zeromq/czmq": {
            "labContributors": {
                "nodes": [
                    "chu11"
                ]
            },
            "nameWithOwner": "zeromq/czmq"
        },
        "zeromq/libzmq": {
            "labContributors": {
                "nodes": [
                    "nightlark"
                ]
            },
            "nameWithOwner": "zeromq/libzmq"
        },
        "zfsonlinux/zfsonlinux.github.com": {
            "labContributors": {
                "nodes": [
                    "behlendorf",
                    "tonyhutter"
                ]
            },
            "nameWithOwner": "zfsonlinux/zfsonlinux.github.com"
        }
    }
}